{"is_source_file": true, "format": "JavaScript", "description": "React component for the checkout page of an e-commerce application, handling order placement, delivery address input, and order summary.", "external_files": ["../components/Button", "../components/Input", "../context/AuthContext", "../context/CartContext", "../context/OrdersContext", "../utils/format", "react", "react-router-dom"], "external_methods": ["useNavigate", "useAuth", "useCart", "useOrders", "formatCurrency"], "published": [], "classes": [], "methods": [{"name": "CheckoutPage", "description": "Main React functional component rendering the checkout page, managing form state, validation, and order submission."}, {"name": "submit(e)", "scope": "CheckoutPage", "scopeKind": "function", "description": "unavailable"}], "calls": ["useNavigate()", "useAuth()", "useCart()", "useOrders()", "formatCurrency()", "setForm()", "setError()", "setPlacing()", "placeOrder()", "clearCart()", "navigate()"], "search-terms": ["CheckoutPage", "orderPayload", "useMemo", "placeOrder", "deliveryAddress", "order summary", "cart validation", "React form handling"], "state": 2, "file_id": 35, "knowledge_revision": 78, "git_revision": "38bed2a6d5dc6df48894a70cf00b2f5dbb34e902", "ctags": [{"_type": "tag", "name": "CheckoutPage", "path": "/home/kavia/workspace/code-generation/mediexpress-41120-41129/react_frontend/src/pages/CheckoutPage.js", "pattern": "/^export default function CheckoutPage() {$/", "language": "JavaScript", "kind": "class", "signature": "()"}, {"_type": "tag", "name": "form", "path": "/home/kavia/workspace/code-generation/mediexpress-41120-41129/react_frontend/src/pages/CheckoutPage.js", "pattern": "/^                  value={form.city}$/", "language": "JavaScript", "kind": "field", "scope": "CheckoutPage.value", "scopeKind": "class"}, {"_type": "tag", "name": "form", "path": "/home/kavia/workspace/code-generation/mediexpress-41120-41129/react_frontend/src/pages/CheckoutPage.js", "pattern": "/^                  value={form.paymentMethod}$/", "language": "JavaScript", "kind": "field", "scope": "CheckoutPage.value", "scopeKind": "class"}, {"_type": "tag", "name": "form", "path": "/home/kavia/workspace/code-generation/mediexpress-41120-41129/react_frontend/src/pages/CheckoutPage.js", "pattern": "/^                  value={form.pincode}$/", "language": "JavaScript", "kind": "field", "scope": "CheckoutPage.value", "scopeKind": "class"}, {"_type": "tag", "name": "form", "path": "/home/kavia/workspace/code-generation/mediexpress-41120-41129/react_frontend/src/pages/CheckoutPage.js", "pattern": "/^                value={form.addressLine1}$/", "language": "JavaScript", "kind": "field", "scope": "CheckoutPage.value", "scopeKind": "class"}, {"_type": "tag", "name": "form", "path": "/home/kavia/workspace/code-generation/mediexpress-41120-41129/react_frontend/src/pages/CheckoutPage.js", "pattern": "/^                value={form.addressLine2}$/", "language": "JavaScript", "kind": "field", "scope": "CheckoutPage.value", "scopeKind": "class"}, {"_type": "tag", "name": "submit", "path": "/home/kavia/workspace/code-generation/mediexpress-41120-41129/react_frontend/src/pages/CheckoutPage.js", "pattern": "/^  async function submit(e) {$/", "language": "JavaScript", "kind": "function", "signature": "(e)", "scope": "CheckoutPage", "scopeKind": "function"}], "hash": "a1798bfb5ad1b6ff2e1cf842bf588d83", "format-version": 4, "code-base-name": "react_frontend", "filename": "react_frontend/src/pages/CheckoutPage.js", "fields": [{"name": "value={form.city}", "scope": "CheckoutPage.value", "scopeKind": "class", "description": "unavailable"}, {"name": "value={form.paymentMethod}", "scope": "CheckoutPage.value", "scopeKind": "class", "description": "unavailable"}, {"name": "value={form.pincode}", "scope": "CheckoutPage.value", "scopeKind": "class", "description": "unavailable"}, {"name": "value={form.addressLine1}", "scope": "CheckoutPage.value", "scopeKind": "class", "description": "unavailable"}, {"name": "value={form.addressLine2}", "scope": "CheckoutPage.value", "scopeKind": "class", "description": "unavailable"}], "revision_history": [{"78": "38bed2a6d5dc6df48894a70cf00b2f5dbb34e902"}]}