{"is_source_file": true, "format": "JavaScript", "description": "This file defines a React context and provider for managing a shopping cart, including persistence via localStorage, state management, and utility functions for cart operations.", "external_files": ["react"], "external_methods": ["React.createContext", "React.useContext", "React.useEffect", "React.useMemo", "React.useState"], "published": ["CartProvider", "useCart"], "classes": [], "methods": [{"name": "loadCart()", "description": "Loads cart data from localStorage and parses it, returning an array of items or an empty array on failure.", "scope": "", "scopeKind": ""}, {"name": "persistCart(items)", "description": "Serializes and saves the cart items to localStorage.", "scope": "", "scopeKind": ""}, {"name": "CartProvider({ children })", "scope": "", "scopeKind": "", "description": "unavailable"}, {"name": "addItem(product, qty = 1)", "scope": "CartProvider", "scopeKind": "function", "description": "unavailable"}, {"name": "clearCart()", "scope": "CartProvider", "scopeKind": "function", "description": "unavailable"}, {"name": "closeCart()", "scope": "CartProvider", "scopeKind": "function", "description": "unavailable"}, {"name": "openCart()", "scope": "CartProvider", "scopeKind": "function", "description": "unavailable"}, {"name": "removeItem(productId)", "scope": "CartProvider", "scopeKind": "function", "description": "unavailable"}, {"name": "toggleCart()", "scope": "CartProvider", "scopeKind": "function", "description": "unavailable"}, {"name": "updateQty(productId, qty)", "scope": "CartProvider", "scopeKind": "function", "description": "unavailable"}, {"name": "useCart()", "scope": "", "scopeKind": "", "description": "unavailable"}], "calls": ["localStorage.getItem", "JSON.parse", "localStorage.setItem", "JSON.stringify"], "search-terms": ["React context for cart", "cart localStorage React", "CartProvider React", "useCart hook", "shopping cart React context"], "state": 2, "file_id": 21, "knowledge_revision": 64, "git_revision": "38bed2a6d5dc6df48894a70cf00b2f5dbb34e902", "ctags": [{"_type": "tag", "name": "CART_KEY", "path": "/home/kavia/workspace/code-generation/mediexpress-41120-41129/react_frontend/src/context/CartContext.js", "pattern": "/^const CART_KEY = \"mediexpress_cart_v1\";$/", "language": "JavaScript", "kind": "constant"}, {"_type": "tag", "name": "CartContext", "path": "/home/kavia/workspace/code-generation/mediexpress-41120-41129/react_frontend/src/context/CartContext.js", "pattern": "/^const CartContext = createContext(null);$/", "language": "JavaScript", "kind": "constant"}, {"_type": "tag", "name": "CartProvider", "path": "/home/kavia/workspace/code-generation/mediexpress-41120-41129/react_frontend/src/context/CartContext.js", "pattern": "/^export function CartProvider({ children }) {$/", "language": "JavaScript", "kind": "function", "signature": "({ children })"}, {"_type": "tag", "name": "addItem", "path": "/home/kavia/workspace/code-generation/mediexpress-41120-41129/react_frontend/src/context/CartContext.js", "pattern": "/^  function addItem(product, qty = 1) {$/", "language": "JavaScript", "kind": "function", "signature": "(product, qty = 1)", "scope": "CartProvider", "scopeKind": "function"}, {"_type": "tag", "name": "clearCart", "path": "/home/kavia/workspace/code-generation/mediexpress-41120-41129/react_frontend/src/context/CartContext.js", "pattern": "/^  function clearCart() {$/", "language": "JavaScript", "kind": "function", "signature": "()", "scope": "CartProvider", "scopeKind": "function"}, {"_type": "tag", "name": "closeCart", "path": "/home/kavia/workspace/code-generation/mediexpress-41120-41129/react_frontend/src/context/CartContext.js", "pattern": "/^  function closeCart() {$/", "language": "JavaScript", "kind": "function", "signature": "()", "scope": "CartProvider", "scopeKind": "function"}, {"_type": "tag", "name": "loadCart", "path": "/home/kavia/workspace/code-generation/mediexpress-41120-41129/react_frontend/src/context/CartContext.js", "pattern": "/^function loadCart() {$/", "language": "JavaScript", "kind": "function", "signature": "()"}, {"_type": "tag", "name": "openCart", "path": "/home/kavia/workspace/code-generation/mediexpress-41120-41129/react_frontend/src/context/CartContext.js", "pattern": "/^  function openCart() {$/", "language": "JavaScript", "kind": "function", "signature": "()", "scope": "CartProvider", "scopeKind": "function"}, {"_type": "tag", "name": "persistCart", "path": "/home/kavia/workspace/code-generation/mediexpress-41120-41129/react_frontend/src/context/CartContext.js", "pattern": "/^function persistCart(items) {$/", "language": "JavaScript", "kind": "function", "signature": "(items)"}, {"_type": "tag", "name": "removeItem", "path": "/home/kavia/workspace/code-generation/mediexpress-41120-41129/react_frontend/src/context/CartContext.js", "pattern": "/^  function removeItem(productId) {$/", "language": "JavaScript", "kind": "function", "signature": "(productId)", "scope": "CartProvider", "scopeKind": "function"}, {"_type": "tag", "name": "toggleCart", "path": "/home/kavia/workspace/code-generation/mediexpress-41120-41129/react_frontend/src/context/CartContext.js", "pattern": "/^  function toggleCart() {$/", "language": "JavaScript", "kind": "function", "signature": "()", "scope": "CartProvider", "scopeKind": "function"}, {"_type": "tag", "name": "updateQty", "path": "/home/kavia/workspace/code-generation/mediexpress-41120-41129/react_frontend/src/context/CartContext.js", "pattern": "/^  function updateQty(productId, qty) {$/", "language": "JavaScript", "kind": "function", "signature": "(productId, qty)", "scope": "CartProvider", "scopeKind": "function"}, {"_type": "tag", "name": "useCart", "path": "/home/kavia/workspace/code-generation/mediexpress-41120-41129/react_frontend/src/context/CartContext.js", "pattern": "/^export function useCart() {$/", "language": "JavaScript", "kind": "function", "signature": "()"}, {"_type": "tag", "name": "value", "path": "/home/kavia/workspace/code-generation/mediexpress-41120-41129/react_frontend/src/context/CartContext.js", "pattern": "/^  return <CartContext.Provider value={value}>{children}<\\/CartContext.Provider>;$/", "language": "JavaScript", "kind": "field", "scope": "Provider", "scopeKind": "class"}], "hash": "8dc04e33cff854ddf15d309b29a443e6", "format-version": 4, "code-base-name": "react_frontend", "filename": "react_frontend/src/context/CartContext.js", "fields": [{"name": "return <CartContext.Provider value={value}>{children}<\\/CartContext.Provider>;", "scope": "Provider", "scopeKind": "class", "description": "unavailable"}], "revision_history": [{"64": "38bed2a6d5dc6df48894a70cf00b2f5dbb34e902"}]}